{
    "parent": {
        "bcid": "ark:/21547/DXv214e4b82fbcaf5d76701ae803839a2938",
        "entity": "Event",
        "country": "USA",
        "eventID": "14e4b82fbcaf5d76701ae803839a2938",
        "habitat": "terrestrial",
        "locality": "Rockaway River WMA_Rock1",
        "projectId": "292",
        "collectorList": "J. Hardin Waddle|Daniel A. Grear|Brad M. Glorioso |Adam R. Backlin|William J. Barichivich|Adrianne B. Brand|Daniel L. Calhoun|Jillian E. Fleming|Andrew E. Dietrich|Patrick M. Kleeman|Marcella A. Cruz",
        "stateProvince": "New Jersey",
        "yearCollected": "2016",
        "expeditionCode": "USGSBsal",
        "monthCollected": "05",
        "decimalLatitude": "40.98859",
        "horizontalDatum": "WGS1984",
        "decimalLongitude": "-74.57244",
        "principalInvestigator": "Hardin Waddle",
        "maximumElevationInMeters": "354",
        "minimumElevationInMeters": "354",
        "coordinateUncertaintyInMeters": "30"
    },
    "record": {
        "bcid": "ark:/21547/DXw21601500071",
        "genus": "Notophthalmus",
        "entity": "Sample",
        "length": "35",
        "eventID": "14e4b82fbcaf5d76701ae803839a2938",
        "lifeStage": "juvenile",
        "projectId": "292",
        "lengthUnits": "millimeters",
        "basisOfRecord": "LivingSpecimen",
        "expeditionCode": "USGSBsal",
        "specificEpithet": "viridescens",
        "materialSampleID": "1601500071",
        "occurrenceRemarks": "2-May-16",
        "associatedReferences": "Waddle, J.H., Grear, D.A., Glorioso, B.M., Backlin, A.R., Barichivich, W.J., Brand, A.B., Calhoun, D.L., Fleming, J.E., Dietrich, A.E., Kleeman, P.M., and Cruz, M.A., 2019, Data from a national survey for the amphibian chytrid fungus Batrachochytrium salamandrivorans: U.S. Geological Survey data release, https://doi.org/10.5066/P9BGQA1T."
    },
    "children": [
        {
            "bcid": "ark:/21547/DXx2430f30e72a8837439945d078c9997861",
            "fatal": "FALSE",
            "entity": "Diagnostics",
            "projectId": "292",
            "sampleType": "swabbing",
            "testMethod": "realtime PCR",
            "diagnosticID": "430f30e72a8837439945d078c9997861",
            "diagnosticLab": "National Wildlife Health Center, Madison, WI",
            "diseaseTested": "Bsal",
            "expeditionCode": "USGSBsal",
            "diseaseDetected": "FALSE",
            "materialSampleID": "1601500071"
        }
    ],
    "projectId": 292
}